bitbadgespy_sdk/__init__.py
bitbadgespy_sdk/api_client.py
bitbadgespy_sdk/api_response.py
bitbadgespy_sdk/configuration.py
bitbadgespy_sdk/exceptions.py
bitbadgespy_sdk/py.typed
bitbadgespy_sdk/rest.py
bitbadgespy_sdk/api/__init__.py
bitbadgespy_sdk/api/accounts_api.py
bitbadgespy_sdk/api/address_lists_api.py
bitbadgespy_sdk/api/applications_api.py
bitbadgespy_sdk/api/claim_alerts_api.py
bitbadgespy_sdk/api/claims_api.py
bitbadgespy_sdk/api/dynamic_stores_api.py
bitbadgespy_sdk/api/maps_and_protocols_api.py
bitbadgespy_sdk/api/miscellanous_api.py
bitbadgespy_sdk/api/plugins_api.py
bitbadgespy_sdk/api/sign_in_with_bit_badges_api.py
bitbadgespy_sdk/api/tokens_api.py
bitbadgespy_sdk/api/transactions_api.py
bitbadgespy_sdk/api/utility_pages_api.py
bitbadgespy_sdk/models/__init__.py
bitbadgespy_sdk/models/account_fetch_details.py
bitbadgespy_sdk/models/account_fetch_details_views_to_fetch_inner.py
bitbadgespy_sdk/models/account_response.py
bitbadgespy_sdk/models/account_response_account.py
bitbadgespy_sdk/models/account_response_account_base_account.py
bitbadgespy_sdk/models/account_response_account_base_account_pub_key.py
bitbadgespy_sdk/models/account_view_key.py
bitbadgespy_sdk/models/additional_query_params.py
bitbadgespy_sdk/models/address_list_view_key.py
bitbadgespy_sdk/models/amino_converter.py
bitbadgespy_sdk/models/amino_msg.py
bitbadgespy_sdk/models/and_group.py
bitbadgespy_sdk/models/asset_condition_group.py
bitbadgespy_sdk/models/asset_details.py
bitbadgespy_sdk/models/asset_details_asset_ids_inner.py
bitbadgespy_sdk/models/attribute.py
bitbadgespy_sdk/models/broadcast_post_body.py
bitbadgespy_sdk/models/broadcast_tx_request.py
bitbadgespy_sdk/models/chain.py
bitbadgespy_sdk/models/challenge_params.py
bitbadgespy_sdk/models/channel.py
bitbadgespy_sdk/models/channels_response.py
bitbadgespy_sdk/models/channels_response_height.py
bitbadgespy_sdk/models/channels_response_pagination.py
bitbadgespy_sdk/models/code_gen_query_params.py
bitbadgespy_sdk-0.1.88.dist-info/METADATA
bitbadgespy_sdk-0.1.88.dist-info/WHEEL
bitbadgespy_sdk-0.1.88.dist-info/top_level.txt
bitbadgespy_sdk-0.1.88.dist-info/RECORD
